AUTHORS
LICENSE
MANIFEST.in
setup.py
povies/__init__.py
povies/povies.py
povies.egg-info/PKG-INFO
povies.egg-info/SOURCES.txt
povies.egg-info/dependency_links.txt
povies.egg-info/not-zip-safe
povies.egg-info/requires.txt
povies.egg-info/top_level.txt