Metadata-Version: 1.1
Name: povies
Version: 1.1.2
Summary: Python wrapper for YTS.ag
Home-page: https://github.com/mczlatan/povies
Author: McZlatan
Author-email: bournethesonofthegun@gmail.com
License: GPLv3
Keywords: yts,yify,torrent,torrents
Platform: UNKNOWN
Classifier: Operating System :: OS Independent
Classifier: Programming Language :: Python
Classifier: Topic :: Software Development :: Libraries :: Python Modules
Classifier: Intended Audience :: Developers
Classifier: Intended Audience :: Information Technology
Classifier: License :: OSI Approved :: GNU General Public License v3 (GPLv3)
Classifier: Topic :: Software Development :: Version Control
Classifier: Topic :: Utilities
